{
  "type": "FeatureCollection",
  "name": "4_26_19_network_changes_dissolved",
  "features": [
    {
      "type": "Feature",
      "properties": {
        "name": "",
        "ID": 110,
        "existing": 0,
        "n_name": "Aleppo",
        "n_from": "Manton",
        "n_to": "Woonasquatucket River Greenway",
        "n_neighbor": "Olneyville",
        "n_owner": "City",
        "n_ntype": "Urban Trail",
        "n_fac_prop": 4,
        "n_Act_pro": "H"
      },
      "geometry": {
        "type": "LineString",
        "coordinates": [
          [
            -71.4479197,
            41.8198617
          ],
          [
            -71.4476024,
            41.8197702
          ],
          [
            -71.4469615,
            41.8195718
          ],
          [
            -71.4465495,
            41.8194421
          ],
          [
            -71.4463511,
            41.8193925
          ],
          [
            -71.4462138,
            41.8193658
          ]
        ]
      }
    },
    {
      "type": "Feature",
      "properties": {
        "name": "",
        "ID": 126,
        "existing": 0,
        "n_name": "Memorial Blvd\/Riverwalk",
        "n_from": "Dyer\/S Water",
        "n_to": "Park",
        "n_neighbor": "Downtown",
        "n_owner": "City",
        "n_ntype": "Urban Trail",
        "n_fac_prop": 2,
        "n_Act_pro": "I"
      },
      "geometry": {
        "type": "LineString",
        "coordinates": [
          [
            -71.4080869,
            41.8240605
          ],
          [
            -71.4081553,
            41.8242265
          ],
          [
            -71.4081318,
            41.8243146
          ],
          [
            -71.4087869,
            41.8254579
          ],
          [
            -71.409076,
            41.8257583
          ],
          [
            -71.4094486,
            41.8260211
          ],
          [
            -71.4104152,
            41.8267839
          ],
          [
            -71.4106552,
            41.8268803
          ]
        ]
      }
    },
    {
      "type": "Feature",
      "properties": {
        "name": "",
        "ID": 126,
        "existing": 1,
        "n_name": "Memorial Blvd\/Riverwalk",
        "n_from": "Dyer\/S Water",
        "n_to": "Park",
        "n_neighbor": "Downtown",
        "n_owner": "City",
        "n_ntype": "Urban Trail",
        "n_fac_prop": 2,
        "n_Act_pro": "I"
      },
      "geometry": {
        "type": "LineString",
        "coordinates": [
          [
            -71.4106552,
            41.8268803
          ],
          [
            -71.4107699,
            41.8269263
          ],
          [
            -71.4112305,
            41.8270143
          ],
          [
            -71.4116406,
            41.827038
          ],
          [
            -71.4120511,
            41.8270039
          ],
          [
            -71.4123702,
            41.8269617
          ],
          [
            -71.4126925,
            41.826886
          ],
          [
            -71.4132603,
            41.8266869
          ],
          [
            -71.4136894,
            41.8265565
          ],
          [
            -71.4138748,
            41.8265156
          ],
          [
            -71.413958,
            41.8265032
          ],
          [
            -71.4140558,
            41.8265107
          ],
          [
            -71.4141413,
            41.8265296
          ],
          [
            -71.4142192,
            41.8265606
          ],
          [
            -71.4142845,
            41.8266023
          ],
          [
            -71.4143348,
            41.8266461
          ],
          [
            -71.4143693,
            41.8266872
          ],
          [
            -71.414395,
            41.8267319
          ],
          [
            -71.4144148,
            41.8267949
          ],
          [
            -71.4144181,
            41.8268434
          ],
          [
            -71.4144122,
            41.8269448
          ],
          [
            -71.4143638,
            41.827225
          ],
          [
            -71.4149561,
            41.8272752
          ],
          [
            -71.4152652,
            41.8273299
          ],
          [
            -71.415515,
            41.827374
          ]
        ]
      }
    },
    {
      "type": "Feature",
      "properties": {
        "name": "Amherst St",
        "ID": 146,
        "existing": 0,
        "n_name": "Amherst\/Tuxedo",
        "n_from": "Valley",
        "n_to": "Atwells",
        "n_neighbor": "Olneyville",
        "n_owner": "City",
        "n_ntype": "Urban Trail",
        "n_fac_prop": 4,
        "n_Act_pro": "H"
      },
      "geometry": {
        "type": "LineString",
        "coordinates": [
          [
            -71.4389201,
            41.8231767
          ],
          [
            -71.4394008,
            41.8232339
          ],
          [
            -71.4397593,
            41.8232797
          ]
        ]
      }
    },
    {
      "type": "Feature",
      "properties": {
        "name": "Angell St",
        "ID": 148,
        "existing": 0,
        "n_name": "S Angell\/Angell",
        "n_from": "Henderson Bridge",
        "n_to": "Hope",
        "n_neighbor": "Wayland, College Hill",
        "n_owner": "City",
        "n_ntype": "Urban Trail",
        "n_fac_prop": 3,
        "n_Act_pro": "E"
      },
      "geometry": {
        "type": "LineString",
        "coordinates": [
          [
            -71.3975078,
            41.8284219
          ],
          [
            -71.3966533,
            41.8285707
          ],
          [
            -71.3956386,
            41.8287462
          ],
          [
            -71.3954783,
            41.8287729
          ],
          [
            -71.3948222,
            41.8288835
          ],
          [
            -71.3939372,
            41.8290361
          ],
          [
            -71.3931285,
            41.8291963
          ],
          [
            -71.3921672,
            41.8293908
          ],
          [
            -71.3921443,
            41.8293947
          ],
          [
            -71.3916636,
            41.8294786
          ],
          [
            -71.3909694,
            41.8296045
          ],
          [
            -71.3909694,
            41.8296083
          ],
          [
            -71.390153,
            41.8297609
          ],
          [
            -71.3895274,
            41.8298791
          ],
          [
            -71.3893214,
            41.8299173
          ],
          [
            -71.3882457,
            41.830108
          ]
        ]
      }
    },
    {
      "type": "Feature",
      "properties": {
        "name": "Angell St",
        "ID": 149,
        "existing": 0,
        "n_name": "Angell",
        "n_from": "Hope",
        "n_to": "Prospect",
        "n_neighbor": "College Hill",
        "n_owner": "City",
        "n_ntype": "Urban Trail",
        "n_fac_prop": 3,
        "n_Act_pro": "D"
      },
      "geometry": {
        "type": "LineString",
        "coordinates": [
          [
            -71.4048091,
            41.8277429
          ],
          [
            -71.4042369,
            41.8277963
          ],
          [
            -71.403184,
            41.8278802
          ],
          [
            -71.4023753,
            41.8279756
          ],
          [
            -71.4006511,
            41.8281205
          ],
          [
            -71.3994685,
            41.8282312
          ],
          [
            -71.3994456,
            41.8282388
          ],
          [
            -71.3990489,
            41.8282769
          ],
          [
            -71.3987742,
            41.8282998
          ],
          [
            -71.3986674,
            41.8283113
          ],
          [
            -71.3975078,
            41.8284219
          ]
        ]
      }
    },
    {
      "type": "Feature",
      "properties": {
        "name": "Bradford St",
        "ID": 152,
        "existing": 0,
        "n_name": "Bradford",
        "n_from": "W Exchange St",
        "n_to": "Broadway",
        "n_neighbor": "Federal Hill",
        "n_owner": "City",
        "n_ntype": "Urban Trail",
        "n_fac_prop": 4,
        "n_Act_pro": "H"
      },
      "geometry": {
        "type": "LineString",
        "coordinates": [
          [
            -71.4215175,
            41.8253358
          ],
          [
            -71.421548,
            41.8250917
          ],
          [
            -71.4215861,
            41.8248246
          ],
          [
            -71.421609,
            41.824611
          ],
          [
            -71.4216395,
            41.8244012
          ],
          [
            -71.4216472,
            41.8243211
          ],
          [
            -71.4216777,
            41.8241418
          ],
          [
            -71.4216777,
            41.8241151
          ],
          [
            -71.4217158,
            41.8238786
          ],
          [
            -71.4217311,
            41.8237909
          ],
          [
            -71.4217616,
            41.8235315
          ],
          [
            -71.4217769,
            41.823253
          ],
          [
            -71.4218226,
            41.8229516
          ],
          [
            -71.4218913,
            41.8224748
          ],
          [
            -71.4219295,
            41.8222154
          ],
          [
            -71.4219447,
            41.8220819
          ],
          [
            -71.4219905,
            41.8215593
          ]
        ]
      }
    },
    {
      "type": "Feature",
      "properties": {
        "name": "Broad St",
        "ID": 150,
        "existing": 0,
        "n_name": "Fricker\/Lockwood",
        "n_from": "Cranston\/Westminster",
        "n_to": "Pine",
        "n_neighbor": "Upper South Providence",
        "n_owner": "City",
        "n_ntype": "Urban Trail",
        "n_fac_prop": 4,
        "n_Act_pro": "H"
      },
      "geometry": {
        "type": "LineString",
        "coordinates": [
          [
            -71.4206019,
            41.81541
          ],
          [
            -71.420663,
            41.815307
          ]
        ]
      }
    },
    {
      "type": "Feature",
      "properties": {
        "name": "Brook St",
        "ID": 144,
        "existing": 0,
        "n_name": "Brook",
        "n_from": "Lloyd",
        "n_to": "Wickenden",
        "n_neighbor": "College Hill, Fox Point",
        "n_owner": "City",
        "n_ntype": "Urban Trail",
        "n_fac_prop": 7,
        "n_Act_pro": "I"
      },
      "geometry": {
        "type": "LineString",
        "coordinates": [
          [
            -71.3982631,
            41.8194993
          ],
          [
            -71.3983241,
            41.8200067
          ],
          [
            -71.3983851,
            41.8205827
          ],
          [
            -71.3984309,
            41.8211396
          ],
          [
            -71.3984691,
            41.8215211
          ],
          [
            -71.398492,
            41.8217958
          ],
          [
            -71.3985911,
            41.8224748
          ],
          [
            -71.3986979,
            41.8230775
          ],
          [
            -71.3988429,
            41.8240388
          ],
          [
            -71.3988811,
            41.8243058
          ],
          [
            -71.398965,
            41.82492
          ],
          [
            -71.3990565,
            41.8256372
          ],
          [
            -71.399171,
            41.8264573
          ],
          [
            -71.3991786,
            41.8265336
          ],
          [
            -71.399232,
            41.8268808
          ],
          [
            -71.3993236,
            41.8274263
          ],
          [
            -71.3993999,
            41.827823
          ],
          [
            -71.3994685,
            41.8282312
          ],
          [
            -71.3994761,
            41.8282769
          ],
          [
            -71.3995372,
            41.8287729
          ],
          [
            -71.3995906,
            41.8292611
          ],
          [
            -71.3997127,
            41.8301347
          ],
          [
            -71.3998118,
            41.8308862
          ],
          [
            -71.3999034,
            41.8315423
          ],
          [
            -71.399911,
            41.8317712
          ]
        ]
      }
    },
    {
      "type": "Feature",
      "properties": {
        "name": "Douglas Ave",
        "ID": 147,
        "existing": 0,
        "n_name": "Douglas",
        "n_from": "Orms",
        "n_to": "Eaton",
        "n_neighbor": "Smith Hill, Elmhurst",
        "n_owner": "City",
        "n_ntype": "Great Street",
        "n_fac_prop": 6,
        "n_Act_pro": "D"
      },
      "geometry": {
        "type": "LineString",
        "coordinates": [
          [
            -71.4159785,
            41.834739
          ],
          [
            -71.4163066,
            41.8347619
          ],
          [
            -71.4164828,
            41.8348076
          ],
          [
            -71.4166471,
            41.834863
          ],
          [
            -71.416759,
            41.8349198
          ],
          [
            -71.4175654,
            41.835235
          ],
          [
            -71.4179469,
            41.8353799
          ],
          [
            -71.4182063,
            41.8354867
          ],
          [
            -71.4184047,
            41.8355706
          ],
          [
            -71.4188014,
            41.8357347
          ],
          [
            -71.4195796,
            41.8360551
          ],
          [
            -71.4196635,
            41.8360894
          ],
          [
            -71.4200068,
            41.8362306
          ],
          [
            -71.4202434,
            41.8363298
          ],
          [
            -71.4215404,
            41.8368753
          ],
          [
            -71.4218379,
            41.8370012
          ],
          [
            -71.4219218,
            41.8370355
          ],
          [
            -71.4223186,
            41.8372072
          ],
          [
            -71.4231502,
            41.8375657
          ],
          [
            -71.4233714,
            41.8376573
          ],
          [
            -71.4235621,
            41.8377412
          ],
          [
            -71.4239055,
            41.8378824
          ],
          [
            -71.4241954,
            41.8380349
          ],
          [
            -71.4247752,
            41.8383821
          ],
          [
            -71.4249354,
            41.8384851
          ],
          [
            -71.4250499,
            41.8385804
          ],
          [
            -71.4250804,
            41.8386033
          ],
          [
            -71.4258204,
            41.8392671
          ],
          [
            -71.4258281,
            41.8392785
          ],
          [
            -71.4264003,
            41.8399118
          ],
          [
            -71.4266444,
            41.8401712
          ],
          [
            -71.4268809,
            41.8404268
          ],
          [
            -71.4270335,
            41.8405908
          ],
          [
            -71.4270717,
            41.8406404
          ],
          [
            -71.4271098,
            41.8406862
          ],
          [
            -71.4271174,
            41.8406938
          ],
          [
            -71.4271556,
            41.8407434
          ],
          [
            -71.4271937,
            41.8408082
          ],
          [
            -71.4272319,
            41.8408731
          ],
          [
            -71.4272624,
            41.8409417
          ]
        ]
      }
    },
    {
      "type": "Feature",
      "properties": {
        "name": "Fricker St",
        "ID": 150,
        "existing": 0,
        "n_name": "Fricker\/Lockwood",
        "n_from": "Cranston\/Westminster",
        "n_to": "Pine",
        "n_neighbor": "Upper South Providence",
        "n_owner": "City",
        "n_ntype": "Urban Trail",
        "n_fac_prop": 4,
        "n_Act_pro": "H"
      },
      "geometry": {
        "type": "LineString",
        "coordinates": [
          [
            -71.4222651,
            41.8171914
          ],
          [
            -71.4216014,
            41.8164018
          ],
          [
            -71.420663,
            41.815307
          ]
        ]
      }
    },
    {
      "type": "Feature",
      "properties": {
        "name": "Friendship St",
        "ID": 4,
        "existing": 0,
        "n_name": "Friendship",
        "n_from": "Broad",
        "n_to": "W Franklin",
        "n_neighbor": "Upper South Providence",
        "n_owner": "City",
        "n_ntype": "Urban Trail",
        "n_fac_prop": 4,
        "n_Act_pro": "H"
      },
      "geometry": {
        "type": "LineString",
        "coordinates": [
          [
            -71.4152843,
            41.8158754
          ],
          [
            -71.4157878,
            41.8153528
          ],
          [
            -71.4160014,
            41.8151353
          ],
          [
            -71.4164515,
            41.8146661
          ],
          [
            -71.4167796,
            41.8143228
          ],
          [
            -71.4170009,
            41.8140901
          ],
          [
            -71.4170314,
            41.8140596
          ],
          [
            -71.4173747,
            41.8137086
          ],
          [
            -71.4179011,
            41.8131479
          ],
          [
            -71.4184047,
            41.8126214
          ],
          [
            -71.4189158,
            41.8120797
          ],
          [
            -71.4192363,
            41.8117517
          ],
          [
            -71.4194423,
            41.8115419
          ],
          [
            -71.4196025,
            41.811374
          ],
          [
            -71.4196101,
            41.8113702
          ],
          [
            -71.4199611,
            41.8110078
          ],
          [
            -71.4202968,
            41.8106378
          ],
          [
            -71.4208613,
            41.8100389
          ],
          [
            -71.4210498,
            41.8099394
          ]
        ]
      }
    },
    {
      "type": "Feature",
      "properties": {
        "name": "Henderson Expy",
        "ID": 2,
        "existing": 0,
        "n_name": "Henderson Bridge",
        "n_from": "Angell\/Waterman",
        "n_to": "East Providence",
        "n_neighbor": "Wayland",
        "n_owner": "RIDOT",
        "n_ntype": "Urban Trail",
        "n_fac_prop": 1,
        "n_Act_pro": "F"
      },
      "geometry": {
        "type": "LineString",
        "coordinates": [
          [
            -71.3829509,
            41.8276284
          ],
          [
            -71.3828975,
            41.8276246
          ],
          [
            -71.382783,
            41.8276132
          ],
          [
            -71.3825847,
            41.8276284
          ],
          [
            -71.3824092,
            41.8276819
          ],
          [
            -71.3820277,
            41.8279298
          ],
          [
            -71.3817225,
            41.8282579
          ],
          [
            -71.3816615,
            41.8283265
          ],
          [
            -71.3813563,
            41.8285783
          ],
          [
            -71.3810969,
            41.8287614
          ],
          [
            -71.3808604,
            41.8288987
          ],
          [
            -71.3806087,
            41.8290094
          ],
          [
            -71.3804027,
            41.8290857
          ],
          [
            -71.3803264,
            41.8291009
          ],
          [
            -71.3801814,
            41.8291314
          ],
          [
            -71.3799678,
            41.829181
          ],
          [
            -71.3798457,
            41.8291963
          ],
          [
            -71.3797618,
            41.8292077
          ],
          [
            -71.379716,
            41.8292115
          ],
          [
            -71.3796397,
            41.8292154
          ],
          [
            -71.3794948,
            41.829223
          ],
          [
            -71.3792506,
            41.8292268
          ],
          [
            -71.3791591,
            41.8292268
          ],
          [
            -71.3783275,
            41.8291887
          ],
          [
            -71.3777324,
            41.8291505
          ],
          [
            -71.3775645,
            41.8291391
          ],
          [
            -71.3758791,
            41.8290332
          ]
        ]
      }
    },
    {
      "type": "Feature",
      "properties": {
        "name": "Lockwood St",
        "ID": 150,
        "existing": 0,
        "n_name": "Fricker\/Lockwood",
        "n_from": "Cranston\/Westminster",
        "n_to": "Pine",
        "n_neighbor": "Upper South Providence",
        "n_owner": "City",
        "n_ntype": "Urban Trail",
        "n_fac_prop": 4,
        "n_Act_pro": "H"
      },
      "geometry": {
        "type": "LineString",
        "coordinates": [
          [
            -71.4180766,
            41.8140748
          ],
          [
            -71.4187404,
            41.8144296
          ],
          [
            -71.4189387,
            41.8145364
          ],
          [
            -71.4194118,
            41.8147844
          ],
          [
            -71.4196025,
            41.8148874
          ],
          [
            -71.4196559,
            41.8149141
          ],
          [
            -71.4202815,
            41.8152498
          ],
          [
            -71.4206019,
            41.81541
          ]
        ]
      }
    },
    {
      "type": "Feature",
      "properties": {
        "name": "Magnolia St",
        "ID": 145,
        "existing": 0,
        "n_name": "New path",
        "n_from": "Dike\/6-10 Connector",
        "n_to": "Pilsudski",
        "n_neighbor": "Olneyville",
        "n_owner": "City",
        "n_ntype": "Urban Trail",
        "n_fac_prop": 1,
        "n_Act_pro": "G"
      },
      "geometry": {
        "type": "LineString",
        "coordinates": [
          [
            -71.4408046,
            41.8141702
          ],
          [
            -71.4413997,
            41.8142312
          ],
          [
            -71.4417582,
            41.8142846
          ]
        ]
      }
    },
    {
      "type": "Feature",
      "properties": {
        "name": "Manton Ave",
        "ID": 10,
        "existing": 0,
        "n_name": "Manton",
        "n_from": "San Souci",
        "n_to": "Aleppo",
        "n_neighbor": "Olneyville",
        "n_owner": "City",
        "n_ntype": "Urban Trail",
        "n_fac_prop": 2,
        "n_Act_pro": "B"
      },
      "geometry": {
        "type": "LineString",
        "coordinates": [
          [
            -71.4435588,
            41.8171037
          ],
          [
            -71.4436198,
            41.8171571
          ],
          [
            -71.4436427,
            41.8171991
          ],
          [
            -71.4436427,
            41.8172029
          ],
          [
            -71.4437419,
            41.8172792
          ],
          [
            -71.4441081,
            41.8175615
          ],
          [
            -71.444192,
            41.8176263
          ],
          [
            -71.4446498,
            41.8179734
          ],
          [
            -71.4453746,
            41.8185342
          ],
          [
            -71.4456569,
            41.8187631
          ],
          [
            -71.4458095,
            41.8188852
          ],
          [
            -71.4459544,
            41.819011
          ],
          [
            -71.4461375,
            41.819259
          ],
          [
            -71.4461528,
            41.8192819
          ],
          [
            -71.4462138,
            41.8193658
          ]
        ]
      }
    },
    {
      "type": "Feature",
      "properties": {
        "name": "new path",
        "ID": 145,
        "existing": 0,
        "n_name": "New path",
        "n_from": "Dike\/6-10 Connector",
        "n_to": "Pilsudski",
        "n_neighbor": "Olneyville",
        "n_owner": "City",
        "n_ntype": "Urban Trail",
        "n_fac_prop": 1,
        "n_Act_pro": "G"
      },
      "geometry": {
        "type": "LineString",
        "coordinates": [
          [
            -71.4408239,
            41.8141716
          ],
          [
            -71.4404815,
            41.8147954
          ],
          [
            -71.4403076,
            41.8154883
          ]
        ]
      }
    },
    {
      "type": "Feature",
      "properties": {
        "name": "Pine St",
        "ID": 5,
        "existing": 0,
        "n_name": "Pine",
        "n_from": "Broad",
        "n_to": "W Franklin",
        "n_neighbor": "Upper South Providence",
        "n_owner": "City",
        "n_ntype": "Urban Trail",
        "n_fac_prop": 4,
        "n_Act_pro": "H"
      },
      "geometry": {
        "type": "LineString",
        "coordinates": [
          [
            -71.4158793,
            41.8163789
          ],
          [
            -71.4167033,
            41.8155168
          ],
          [
            -71.4170543,
            41.8151429
          ],
          [
            -71.4174815,
            41.8147043
          ],
          [
            -71.4174815,
            41.8147004
          ],
          [
            -71.4180766,
            41.8140748
          ],
          [
            -71.4180842,
            41.8140748
          ],
          [
            -71.4186107,
            41.8135331
          ],
          [
            -71.4191142,
            41.8129991
          ],
          [
            -71.4196101,
            41.8124688
          ],
          [
            -71.4196177,
            41.8124536
          ],
          [
            -71.4199382,
            41.8121179
          ],
          [
            -71.4201289,
            41.8119119
          ],
          [
            -71.4203044,
            41.8117326
          ],
          [
            -71.420312,
            41.8117326
          ],
          [
            -71.4206553,
            41.8113817
          ],
          [
            -71.4207088,
            41.8113321
          ],
          [
            -71.4209376,
            41.8110994
          ],
          [
            -71.4212733,
            41.8107751
          ]
        ]
      }
    },
    {
      "type": "Feature",
      "properties": {
        "name": "S Angell St",
        "ID": 148,
        "existing": 0,
        "n_name": "S Angell\/Angell",
        "n_from": "Henderson Bridge",
        "n_to": "Hope",
        "n_neighbor": "Wayland, College Hill",
        "n_owner": "City",
        "n_ntype": "Urban Trail",
        "n_fac_prop": 3,
        "n_Act_pro": "E"
      },
      "geometry": {
        "type": "LineString",
        "coordinates": [
          [
            -71.3756972,
            41.8291862
          ],
          [
            -71.3775569,
            41.8293145
          ],
          [
            -71.3779613,
            41.8293412
          ],
          [
            -71.3785029,
            41.8293641
          ],
          [
            -71.3791438,
            41.8294023
          ],
          [
            -71.3793345,
            41.8294099
          ],
          [
            -71.3795558,
            41.8294175
          ],
          [
            -71.3796016,
            41.8294175
          ],
          [
            -71.3796092,
            41.8294175
          ],
          [
            -71.3797313,
            41.8294175
          ],
          [
            -71.3798152,
            41.8294175
          ],
          [
            -71.3799067,
            41.8294175
          ],
          [
            -71.3801433,
            41.8294137
          ],
          [
            -71.3802501,
            41.8294023
          ],
          [
            -71.3803187,
            41.8293947
          ],
          [
            -71.3805171,
            41.8293756
          ],
          [
            -71.3807078,
            41.8293451
          ],
          [
            -71.3809291,
            41.8293107
          ],
          [
            -71.381158,
            41.8292497
          ],
          [
            -71.3818294,
            41.8290551
          ],
          [
            -71.3820659,
            41.829017
          ],
          [
            -71.3822642,
            41.8290017
          ],
          [
            -71.3824397,
            41.8290132
          ],
          [
            -71.3826228,
            41.8290361
          ],
          [
            -71.3827144,
            41.8290475
          ],
          [
            -71.3828975,
            41.8290818
          ],
          [
            -71.3832561,
            41.8291543
          ],
          [
            -71.3842708,
            41.8293527
          ],
          [
            -71.3850337,
            41.8294976
          ],
          [
            -71.3854838,
            41.8295816
          ],
          [
            -71.3859111,
            41.8296617
          ],
          [
            -71.386674,
            41.8298105
          ],
          [
            -71.3877498,
            41.8300126
          ],
          [
            -71.3879481,
            41.8300508
          ],
          [
            -71.3882457,
            41.830108
          ]
        ]
      }
    },
    {
      "type": "Feature",
      "properties": {
        "name": "Tuxedo Ave",
        "ID": 146,
        "existing": 0,
        "n_name": "Amherst\/Tuxedo",
        "n_from": "Valley",
        "n_to": "Atwells",
        "n_neighbor": "Olneyville",
        "n_owner": "City",
        "n_ntype": "Urban Trail",
        "n_fac_prop": 4,
        "n_Act_pro": "H"
      },
      "geometry": {
        "type": "LineString",
        "coordinates": [
          [
            -71.4386226,
            41.8245462
          ],
          [
            -71.4386683,
            41.8243325
          ],
          [
            -71.4387675,
            41.8238595
          ],
          [
            -71.4389201,
            41.8231767
          ]
        ]
      }
    },
    {
      "type": "Feature",
      "properties": {
        "name": "W Exchange St",
        "ID": 152,
        "existing": 0,
        "n_name": "Bradford",
        "n_from": "W Exchange St",
        "n_to": "Broadway",
        "n_neighbor": "Federal Hill",
        "n_owner": "City",
        "n_ntype": "Urban Trail",
        "n_fac_prop": 4,
        "n_Act_pro": "H"
      },
      "geometry": {
        "type": "LineString",
        "coordinates": [
          [
            -71.4215175,
            41.8253358
          ],
          [
            -71.4218303,
            41.8253587
          ],
          [
            -71.4228068,
            41.825435
          ],
          [
            -71.423585,
            41.8254808
          ],
          [
            -71.4240275,
            41.8255113
          ],
          [
            -71.4240809,
            41.8255151
          ],
          [
            -71.4244243,
            41.8255304
          ],
          [
            -71.4247142,
            41.8255456
          ],
          [
            -71.4249125,
            41.8255494
          ],
          [
            -71.4250194,
            41.8255418
          ],
          [
            -71.4252482,
            41.8255304
          ],
          [
            -71.4254924,
            41.8255037
          ],
          [
            -71.4256984,
            41.8254731
          ],
          [
            -71.4258281,
            41.8254503
          ]
        ]
      }
    },
    {
      "type": "Feature",
      "properties": {
        "name": "Waterman St",
        "ID": 58,
        "existing": 0,
        "n_name": "Waterman",
        "n_from": "Hope",
        "n_to": "Butler",
        "n_neighbor": "Wayland",
        "n_owner": "City",
        "n_ntype": "Urban Trail",
        "n_fac_prop": 3,
        "n_Act_pro": "E"
      },
      "geometry": {
        "type": "LineString",
        "coordinates": [
          [
            -71.3972331,
            41.8276017
          ],
          [
            -71.3954783,
            41.8276399
          ],
          [
            -71.3948527,
            41.8276475
          ],
          [
            -71.3938838,
            41.8276475
          ],
          [
            -71.3929072,
            41.8278039
          ],
          [
            -71.3916636,
            41.8280328
          ],
          [
            -71.390771,
            41.828193
          ],
          [
            -71.3907481,
            41.8282007
          ],
          [
            -71.3903666,
            41.8282693
          ],
          [
            -71.3895579,
            41.8284143
          ],
          [
            -71.388383,
            41.8286241
          ],
          [
            -71.3883754,
            41.8286203
          ],
          [
            -71.3870784,
            41.828399
          ],
          [
            -71.3863536,
            41.8282617
          ],
          [
            -71.3859111,
            41.8281816
          ],
          [
            -71.3854991,
            41.8281015
          ]
        ]
      }
    },
    {
      "type": "Feature",
      "properties": {
        "name": "Waterman St",
        "ID": 59,
        "existing": 0,
        "n_name": "Waterman",
        "n_from": "Prospect",
        "n_to": "Hope",
        "n_neighbor": "Wayland",
        "n_owner": "City",
        "n_ntype": "Urban Trail",
        "n_fac_prop": 3,
        "n_Act_pro": "D"
      },
      "geometry": {
        "type": "LineString",
        "coordinates": [
          [
            -71.4047175,
            41.8269304
          ],
          [
            -71.4041224,
            41.8269838
          ],
          [
            -71.4038325,
            41.8270067
          ],
          [
            -71.4030391,
            41.8270753
          ],
          [
            -71.401826,
            41.8271745
          ],
          [
            -71.4005366,
            41.8273042
          ],
          [
            -71.4005061,
            41.827308
          ],
          [
            -71.3993236,
            41.8274263
          ],
          [
            -71.3993083,
            41.8274263
          ],
          [
            -71.3972331,
            41.8276017
          ]
        ]
      }
    }
  ]
}